03_week/08_sram/spsram.v
// ==================================================
//	[ ZARAM OJT. ]
//	* Author		: Seok Jin Son (sonsj98@zaram.com)
//	* Filename		: spsram.v
//	* Date			: 2024-06-26 14:26:32
//	* Description	:
// ==================================================

module spsram 
#(
	parameter	BW_DATA	=	32,
	parameter	BW_ADDR	=	5
)
(
	output	[BW_DATA-1:0]	o_data,
	input	[BW_DATA-1:0]	i_data,
	input	[BW_ADDR-1:0]	i_addr,
	input					i_wen,
	input					i_cen,
	input					i_oen,
	input					i_clk
);
	
	//Memory Write
	reg	[BW_DATA-1:0]	mem[0:2**BW_ADDR-1];
	always @(posedge i_clk) begin
		if(i_cen && i_wen) begin
			mem[i_addr]	<=	i_data;
		end else begin
			mem[i_addr] <= mem[i_addr];
		end
	end


	//Memory Read
	`ifdef	SPSRAM_ASYNC
		assign	o_data	=	!i_oen	?	'bz	:
							i_cen	&&	!i_wen	?	mem[i_addr]	:	'bx;

	`else
		reg	[BW_DATA-1:0]	o_data;
		always @(posedge i_clk) begin
			if(i_oen) begin
				if(i_cen && !i_wen) begin
					o_data	<=	mem[i_addr];
				end	else begin
					o_data	<=	'bx;
				end
			end else begin
				o_data	<= 'bz;
			end
		end
	`endif

endmodule

03_week/08_sram/spsram_doubled.v
// ==================================================
//	[ ZARAM OJT. ]
//	* Author		: Seok Jin Son (sonsj98@zaram.com)
//	* Filename		: spsram_doubled.v
//	* Date			: 2024-06-26 15:03:06
//	* Description	:
// ==================================================

`include	"spsram.v"

module spsram_doubled 
#(
	parameter	BW_DATA	=	32,
	parameter	BW_ADDR	=	5
)
(
	output	[BW_DATA-1:0]	o_data,
	input	[BW_DATA-1:0]	i_data,
	input	[BW_ADDR-1:0]	i_addr,
	input					i_wen,
	input					i_cen,
	input					i_oen,
	input					i_clk
);
	

	spsram
	#(
	.BW_DATA			(BW_DATA			),
	.BW_ADDR			(BW_ADDR-1			)
	)
	u_spsram_0(
	.o_data				(o_data				),
	.i_data				(i_data				),
	.i_addr				(i_addr[3:0]		),
	.i_wen				(i_wen				),
	.i_cen				(~i_addr[4]			),
	.i_oen				(~i_addr[4]			),
	.i_clk				(i_clk				)
	);


	spsram
	#(
	.BW_DATA			(BW_DATA			),
	.BW_ADDR			(BW_ADDR-1			)
	)	
	u_spsram_1(
	.o_data				(o_data				),
	.i_data				(i_data				),
	.i_addr				(i_addr[3:0]		),
	.i_wen				(i_wen				),
	.i_cen				(i_addr[4]			),
	.i_oen				(i_addr[4]			),
	.i_clk				(i_clk				)
	);


endmodule

03_week/08_sram/spsram_doubled_tb.v
// ==================================================
//	[ ZARAM OJT. ]
//	* Author		: Seok Jin Son (sonsj98@zaram.com)
//	* Filename		: spsram_doubled_tb.v
//	* Date			: 2024-06-26 15:12:43
//	* Description	:
// ==================================================


// --------------------------------------------------
//	Define Global Variables
// --------------------------------------------------
`define	CLKFREQ		100		// Clock Freq. (Unit: MHz)
`define	SIMCYCLE	32	// Sim. Cycles
`define BW_DATA		32		// Bitwidth of ~~
`define BW_ADDR		5		// Bitwidth of ~~

`define SPSRAM_ASYNC

// --------------------------------------------------
//	Includes
// --------------------------------------------------
`include	"spsram_doubled.v"

module spsram_doubled_tb;
// --------------------------------------------------
//	DUT Signals & Instantiate
// --------------------------------------------------
	wire	[`BW_DATA-1:0]	o_data;
	reg		[`BW_DATA-1:0]	i_data;
	reg		[`BW_ADDR-1:0]	i_addr;
	reg						i_wen;
	reg						i_cen;
	reg						i_oen;
	reg						i_clk;

	spsram_doubled
	#(
	.BW_DATA			(`BW_DATA			),
	.BW_ADDR			(`BW_ADDR			)
	)
	u_spsram_doubled(
	.o_data				(o_data				),
	.i_data				(i_data				),
	.i_addr				(i_addr				),
	.i_wen				(i_wen				),
	.i_cen				(i_cen				),
	.i_oen				(i_oen				),
	.i_clk				(i_clk				)
	);


// ----------------------------------
// Clock
// ----------------------------------
	always	#(500/`CLKFREQ) i_clk = ~ i_clk;

// ----------------------------------
// Tasks
// ----------------------------------
	reg [8*32-1:0] 	taskState;

	task init;
		begin
			taskState	= "Init";
			i_data  	= 0;
			i_addr  	= 0;
			i_wen		= 0;
			i_cen		= 0;
			i_oen		= 0;
			i_clk		= 0;
		end
	endtask

	task memWR;
		input	[`BW_ADDR-1:0]	ti_addr;
		input	[`BW_DATA-1:0]	ti_data;
		begin
			@(negedge i_clk) begin
				taskState	= "WR";
				i_data		= ti_data;
				i_addr		= ti_addr;
				i_wen		= 1;
				i_cen		= 1;
				//i_oen		= 0;
			end
		end
	endtask

	task memRD;
		input	[`BW_ADDR-1:0] ti_addr;
		begin
			@(negedge i_clk) begin
				taskState	= "RD";
				i_addr		= ti_addr;
				i_wen		= 0;
				i_cen		= 1;
				i_oen		= 1;
			end
		end
	endtask


// --------------------------------------------------
//	Test Stimulus
// --------------------------------------------------
	integer		i, j;
	initial begin
		init();
		#(4*1000/`CLKFREQ);

		for (i=0; i<`SIMCYCLE; i++) begin
			memWR(i, i);
		end
		for (i=0; i<`SIMCYCLE; i++) begin
			memRD(i);
		end
		$finish;
	end

// --------------------------------------------------
//	Dump VCD
// --------------------------------------------------
	reg	[8*32-1:0]	vcd_file;
	initial begin
		if ($value$plusargs("vcd_file=%s", vcd_file)) begin
			$dumpfile(vcd_file);
			$dumpvars;
		end else begin
			$dumpfile("spsram_doubled_tb.vcd");
			$dumpvars;
		end
	end

endmodule

03_week/08_sram/vcd/spsram_doubled.vcd
$date
	Mon Jul  1 11:27:37 2024
$end
$version
	Icarus Verilog
$end
$timescale
	1ps
$end
$scope module spsram_doubled_tb $end
$var wire 32 ! o_data [31:0] $end
$var reg 5 " i_addr [4:0] $end
$var reg 1 # i_cen $end
$var reg 1 $ i_clk $end
$var reg 32 % i_data [31:0] $end
$var reg 1 & i_oen $end
$var reg 1 ' i_wen $end
$var reg 256 ( taskState [255:0] $end
$var reg 256 ) vcd_file [255:0] $end
$var integer 32 * i [31:0] $end
$scope module u_spsram_doubled $end
$var wire 5 + i_addr [4:0] $end
$var wire 1 # i_cen $end
$var wire 1 $ i_clk $end
$var wire 32 , i_data [31:0] $end
$var wire 1 & i_oen $end
$var wire 1 ' i_wen $end
$var wire 32 - o_data [31:0] $end
$scope module u_spsram_0 $end
$var wire 4 . i_addr [3:0] $end
$var wire 1 / i_cen $end
$var wire 1 $ i_clk $end
$var wire 32 0 i_data [31:0] $end
$var wire 1 1 i_oen $end
$var wire 1 ' i_wen $end
$var wire 32 2 o_data [31:0] $end
$upscope $end
$scope module u_spsram_1 $end
$var wire 4 3 i_addr [3:0] $end
$var wire 1 4 i_cen $end
$var wire 1 $ i_clk $end
$var wire 32 5 i_data [31:0] $end
$var wire 1 6 i_oen $end
$var wire 1 ' i_wen $end
$var wire 32 7 o_data [31:0] $end
$upscope $end
$upscope $end
$scope task init $end
$upscope $end
$scope task memRD $end
$var reg 5 8 ti_addr [4:0] $end
$upscope $end
$scope task memWR $end
$var reg 5 9 ti_addr [4:0] $end
$var reg 32 : ti_data [31:0] $end
$upscope $end
$upscope $end
$enddefinitions $end
#0
$dumpvars
bx :
bx 9
bx 8
bx 7
06
b0 5
04
b0 3
bx 2
11
b0 0
1/
b0 .
bx -
b0 ,
b0 +
bx *
b1011100010111101110110011000110110010000101111011100110111000001110011011100100110000101101101010111110110010001101111011101010110001001101100011001010110010000101110011101100110001101100100 )
b1001001011011100110100101110100 (
0'
0&
b0 %
0$
0#
b0 "
bx !
$end
#5000
1$
#10000
0$
#15000
1$
#20000
0$
#25000
1$
#30000
0$
#35000
1$
#40000
1#
1'
b101011101010010 (
0$
b1 :
b1 9
b1 *
#45000
1$
#50000
b1 .
b1 3
b10 :
b10 9
b10 *
b1 "
b1 +
b1 %
b1 ,
b1 0
b1 5
0$
#55000
1$
#60000
b10 .
b10 3
b11 :
b11 9
b11 *
b10 "
b10 +
b10 %
b10 ,
b10 0
b10 5
0$
#65000
1$
#70000
b11 .
b11 3
b100 :
b100 9
b100 *
b11 "
b11 +
b11 %
b11 ,
b11 0
b11 5
0$
#75000
1$
#80000
b100 .
b100 3
b101 :
b101 9
b101 *
b100 "
b100 +
b100 %
b100 ,
b100 0
b100 5
0$
#85000
1$
#90000
b101 .
b101 3
b110 :
b110 9
b110 *
b101 "
b101 +
b101 %
b101 ,
b101 0
b101 5
0$
#95000
1$
#100000
b110 .
b110 3
b111 :
b111 9
b111 *
b110 "
b110 +
b110 %
b110 ,
b110 0
b110 5
0$
#105000
1$
#110000
b111 .
b111 3
b1000 :
b1000 9
b1000 *
b111 "
b111 +
b111 %
b111 ,
b111 0
b111 5
0$
#115000
1$
#120000
b1000 .
b1000 3
b1001 :
b1001 9
b1001 *
b1000 "
b1000 +
b1000 %
b1000 ,
b1000 0
b1000 5
0$
#125000
1$
#130000
b1001 .
b1001 3
b1010 :
b1010 9
b1010 *
b1001 "
b1001 +
b1001 %
b1001 ,
b1001 0
b1001 5
0$
#135000
1$
#140000
b1010 .
b1010 3
b1011 :
b1011 9
b1011 *
b1010 "
b1010 +
b1010 %
b1010 ,
b1010 0
b1010 5
0$
#145000
1$
#150000
b1011 .
b1011 3
b1100 :
b1100 9
b1100 *
b1011 "
b1011 +
b1011 %
b1011 ,
b1011 0
b1011 5
0$
#155000
1$
#160000
b1100 .
b1100 3
b1101 :
b1101 9
b1101 *
b1100 "
b1100 +
b1100 %
b1100 ,
b1100 0
b1100 5
0$
#165000
1$
#170000
b1101 .
b1101 3
b1110 :
b1110 9
b1110 *
b1101 "
b1101 +
b1101 %
b1101 ,
b1101 0
b1101 5
0$
#175000
1$
#180000
b1110 .
b1110 3
b1111 :
b1111 9
b1111 *
b1110 "
b1110 +
b1110 %
b1110 ,
b1110 0
b1110 5
0$
#185000
1$
#190000
b1111 .
b1111 3
b10000 :
b10000 9
b10000 *
b1111 "
b1111 +
b1111 %
b1111 ,
b1111 0
b1111 5
0$
#195000
1$
#200000
0/
01
b0 .
b0 3
14
16
b10001 :
b10001 9
b10001 *
b10000 "
b10000 +
b10000 %
b10000 ,
b10000 0
b10000 5
0$
#205000
1$
#210000
b1 .
b1 3
b10010 :
b10010 9
b10010 *
b10001 "
b10001 +
b10001 %
b10001 ,
b10001 0
b10001 5
0$
#215000
1$
#220000
b10 .
b10 3
b10011 :
b10011 9
b10011 *
b10010 "
b10010 +
b10010 %
b10010 ,
b10010 0
b10010 5
0$
#225000
1$
#230000
b11 .
b11 3
b10100 :
b10100 9
b10100 *
b10011 "
b10011 +
b10011 %
b10011 ,
b10011 0
b10011 5
0$
#235000
1$
#240000
b100 .
b100 3
b10101 :
b10101 9
b10101 *
b10100 "
b10100 +
b10100 %
b10100 ,
b10100 0
b10100 5
0$
#245000
1$
#250000
b101 .
b101 3
b10110 :
b10110 9
b10110 *
b10101 "
b10101 +
b10101 %
b10101 ,
b10101 0
b10101 5
0$
#255000
1$
#260000
b110 .
b110 3
b10111 :
b10111 9
b10111 *
b10110 "
b10110 +
b10110 %
b10110 ,
b10110 0
b10110 5
0$
#265000
1$
#270000
b111 .
b111 3
b11000 :
b11000 9
b11000 *
b10111 "
b10111 +
b10111 %
b10111 ,
b10111 0
b10111 5
0$
#275000
1$
#280000
b1000 .
b1000 3
b11001 :
b11001 9
b11001 *
b11000 "
b11000 +
b11000 %
b11000 ,
b11000 0
b11000 5
0$
#285000
1$
#290000
b1001 .
b1001 3
b11010 :
b11010 9
b11010 *
b11001 "
b11001 +
b11001 %
b11001 ,
b11001 0
b11001 5
0$
#295000
1$
#300000
b1010 .
b1010 3
b11011 :
b11011 9
b11011 *
b11010 "
b11010 +
b11010 %
b11010 ,
b11010 0
b11010 5
0$
#305000
1$
#310000
b1011 .
b1011 3
b11100 :
b11100 9
b11100 *
b11011 "
b11011 +
b11011 %
b11011 ,
b11011 0
b11011 5
0$
#315000
1$
#320000
b1100 .
b1100 3
b11101 :
b11101 9
b11101 *
b11100 "
b11100 +
b11100 %
b11100 ,
b11100 0
b11100 5
0$
#325000
1$
#330000
b1101 .
b1101 3
b11110 :
b11110 9
b11110 *
b11101 "
b11101 +
b11101 %
b11101 ,
b11101 0
b11101 5
0$
#335000
1$
#340000
b1110 .
b1110 3
b11111 :
b11111 9
b11111 *
b11110 "
b11110 +
b11110 %
b11110 ,
b11110 0
b11110 5
0$
#345000
1$
#350000
b1111 .
b1111 3
b0 8
b0 *
b11111 "
b11111 +
b11111 %
b11111 ,
b11111 0
b11111 5
0$
#355000
1$
#360000
1/
11
b0 !
b0 -
b0 2
b0 7
b0 .
b0 3
04
06
b1 8
b1 *
1&
0'
b0 "
b0 +
b101001001000100 (
0$
#365000
1$
#370000
b1 !
b1 -
b1 2
b1 7
b1 .
b1 3
b10 8
b10 *
b1 "
b1 +
0$
#375000
1$
#380000
b10 !
b10 -
b10 2
b10 7
b10 .
b10 3
b11 8
b11 *
b10 "
b10 +
0$
#385000
1$
#390000
b11 !
b11 -
b11 2
b11 7
b11 .
b11 3
b100 8
b100 *
b11 "
b11 +
0$
#395000
1$
#400000
b100 !
b100 -
b100 2
b100 7
b100 .
b100 3
b101 8
b101 *
b100 "
b100 +
0$
#405000
1$
#410000
b101 !
b101 -
b101 2
b101 7
b101 .
b101 3
b110 8
b110 *
b101 "
b101 +
0$
#415000
1$
#420000
b110 !
b110 -
b110 2
b110 7
b110 .
b110 3
b111 8
b111 *
b110 "
b110 +
0$
#425000
1$
#430000
b111 !
b111 -
b111 2
b111 7
b111 .
b111 3
b1000 8
b1000 *
b111 "
b111 +
0$
#435000
1$
#440000
b1000 !
b1000 -
b1000 2
b1000 7
b1000 .
b1000 3
b1001 8
b1001 *
b1000 "
b1000 +
0$
#445000
1$
#450000
b1001 !
b1001 -
b1001 2
b1001 7
b1001 .
b1001 3
b1010 8
b1010 *
b1001 "
b1001 +
0$
#455000
1$
#460000
b1010 !
b1010 -
b1010 2
b1010 7
b1010 .
b1010 3
b1011 8
b1011 *
b1010 "
b1010 +
0$
#465000
1$
#470000
b1011 !
b1011 -
b1011 2
b1011 7
b1011 .
b1011 3
b1100 8
b1100 *
b1011 "
b1011 +
0$
#475000
1$
#480000
b1100 !
b1100 -
b1100 2
b1100 7
b1100 .
b1100 3
b1101 8
b1101 *
b1100 "
b1100 +
0$
#485000
1$
#490000
b1101 !
b1101 -
b1101 2
b1101 7
b1101 .
b1101 3
b1110 8
b1110 *
b1101 "
b1101 +
0$
#495000
1$
#500000
b1110 !
b1110 -
b1110 2
b1110 7
b1110 .
b1110 3
b1111 8
b1111 *
b1110 "
b1110 +
0$
#505000
1$
#510000
b1111 !
b1111 -
b1111 2
b1111 7
b1111 .
b1111 3
b10000 8
b10000 *
b1111 "
b1111 +
0$
#515000
1$
#520000
0/
01
b10000 !
b10000 -
b10000 2
b10000 7
b0 .
b0 3
14
16
b10001 8
b10001 *
b10000 "
b10000 +
0$
#525000
1$
#530000
b10001 !
b10001 -
b10001 2
b10001 7
b1 .
b1 3
b10010 8
b10010 *
b10001 "
b10001 +
0$
#535000
1$
#540000
b10010 !
b10010 -
b10010 2
b10010 7
b10 .
b10 3
b10011 8
b10011 *
b10010 "
b10010 +
0$
#545000
1$
#550000
b10011 !
b10011 -
b10011 2
b10011 7
b11 .
b11 3
b10100 8
b10100 *
b10011 "
b10011 +
0$
#555000
1$
#560000
b10100 !
b10100 -
b10100 2
b10100 7
b100 .
b100 3
b10101 8
b10101 *
b10100 "
b10100 +
0$
#565000
1$
#570000
b10101 !
b10101 -
b10101 2
b10101 7
b101 .
b101 3
b10110 8
b10110 *
b10101 "
b10101 +
0$
#575000
1$
#580000
b10110 !
b10110 -
b10110 2
b10110 7
b110 .
b110 3
b10111 8
b10111 *
b10110 "
b10110 +
0$
#585000
1$
#590000
b10111 !
b10111 -
b10111 2
b10111 7
b111 .
b111 3
b11000 8
b11000 *
b10111 "
b10111 +
0$
#595000
1$
#600000
b11000 !
b11000 -
b11000 2
b11000 7
b1000 .
b1000 3
b11001 8
b11001 *
b11000 "
b11000 +
0$
#605000
1$
#610000
b11001 !
b11001 -
b11001 2
b11001 7
b1001 .
b1001 3
b11010 8
b11010 *
b11001 "
b11001 +
0$
#615000
1$
#620000
b11010 !
b11010 -
b11010 2
b11010 7
b1010 .
b1010 3
b11011 8
b11011 *
b11010 "
b11010 +
0$
#625000
1$
#630000
b11011 !
b11011 -
b11011 2
b11011 7
b1011 .
b1011 3
b11100 8
b11100 *
b11011 "
b11011 +
0$
#635000
1$
#640000
b11100 !
b11100 -
b11100 2
b11100 7
b1100 .
b1100 3
b11101 8
b11101 *
b11100 "
b11100 +
0$
#645000
1$
#650000
b11101 !
b11101 -
b11101 2
b11101 7
b1101 .
b1101 3
b11110 8
b11110 *
b11101 "
b11101 +
0$
#655000
1$
#660000
b11110 !
b11110 -
b11110 2
b11110 7
b1110 .
b1110 3
b11111 8
b11111 *
b11110 "
b11110 +
0$
#665000
1$
#670000
b11111 !
b11111 -
b11111 2
b11111 7
b1111 .
b1111 3
b100000 *
b11111 "
b11111 +
0$
