03_week/07_fsm_seq_detect/mealy_machine/seq_detect_mealy.v
module seq_detect_mealy 
(
	output	reg		o_out,
	input			i_seq,
	input			i_clk,
	input			i_rstn
);
	
	reg	[2:0]	cState;
	reg	[2:0]	nState;
	reg			seq;

	//States
	localparam	S_IDLE	=	3'b000;
	localparam	S_H		=	3'b001;
	localparam	S_HL	=	3'b010;
	localparam	S_HLH	=	3'b011;


	//State Register
	always @(posedge i_clk or negedge i_rstn) begin
		if(!i_rstn) begin
			cState	<= S_IDLE;
			seq		<= 1'b0;
		end else begin
			cState	<= nState;
			seq		<= i_seq;
		end
	end

	//'Next State' Comb. logic
	always @(*) begin
		if(seq == 1'b0) begin
			case(cState)
				S_IDLE	:	nState	=	S_IDLE;
				S_H	  	:	nState	=	S_HL;
				S_HL  	:	nState	=	S_IDLE;
				S_HLH 	:	nState	=	S_HL;
			endcase
		end else begin
			case(cState)
				S_IDLE	:	nState	=	S_H;
                S_H	  	:	nState	=	S_H;
                S_HL  	:	nState	=	S_HLH;
                S_HLH 	:	nState	=	S_H;
			endcase
		end
	end

	//'Output' Comb. Logic
	always @(*) begin
		case(cState)
			S_HLH	:	o_out	= (seq) ? 1'b1 : 1'b0;
			default	:	o_out	= 1'b0;
		endcase
	end

	//DEBUG
	`ifdef DEBUG
		reg [32*8-1:0]	stateMonitor;
		always @(*) begin
			case(cState)
			S_IDLE	:	stateMonitor	=	"S_IDLE";
            S_H	  	:	stateMonitor	=	"S_H";
            S_HL  	:	stateMonitor	=	"S_HL";
            S_HLH 	:	stateMonitor	=	"S_HLH";
			endcase
		end
	`endif


endmodule

03_week/07_fsm_seq_detect/mealy_machine/seq_detect_mealy_tb.v

// --------------------------------------------------
//	Define Global Variables
// --------------------------------------------------
`define	CLKFREQ		100		// Clock Freq. (Unit: MHz)
`define	SIMCYCLE	50	// Sim. Cycles
`define DEBUG

// --------------------------------------------------
//	Includes
// --------------------------------------------------
`include	"seq_detect_mealy.v"

module seq_detect_mealy_tb;
// --------------------------------------------------
//	DUT Signals & Instantiate
// --------------------------------------------------
	wire			o_out;
	reg				i_seq;
	reg				i_clk;
	reg				i_rstn;

	seq_detect_mealy
	u_seq_detect_mealy(
	.o_out				(o_out				),
	.i_seq				(i_seq				),
	.i_clk				(i_clk				),
	.i_rstn				(i_rstn				)
	);



// ----------------------------------
// Clock
// ----------------------------------
	always	#(500/`CLKFREQ) i_clk = ~ i_clk;

// ----------------------------------
// Tasks
// ----------------------------------
	reg [8*32-1:0] 	taskState;

	task init;
		begin
			taskState	= "Init";
			i_seq		= 0;
			i_clk		= 0;
			i_rstn		= 0;
		end
	endtask

	task resetNCycles;
		input	[9:0]	n;
		begin
			taskState		= "Reset_ON";
			#(n*1000/`CLKFREQ);
			i_rstn = 1;
			taskState		= "Reset_OFF";
		end
	endtask
// --------------------------------------------------
//	Test Stimulus
// --------------------------------------------------
	integer		i, j;
	initial begin
		init();
		resetNCycles(4);

		for (i=0; i<`SIMCYCLE; i++) begin
			i_seq	= $urandom_range(0,1);
			#(1000/`CLKFREQ);
		end
		#(1000/`CLKFREQ);
		$finish;
	end

// --------------------------------------------------
//	Dump VCD
// --------------------------------------------------
	reg	[8*32-1:0]	vcd_file;
	initial begin
		if ($value$plusargs("vcd_file=%s", vcd_file)) begin
			$dumpfile(vcd_file);
			$dumpvars;
		end else begin
			$dumpfile("seq_detect_mealy_tb.vcd");
			$dumpvars;
		end
	end

endmodule

03_week/07_fsm_seq_detect/mealy_machine/vcd/seq_detect_mealy.vcd
$date
	Tue Jul  2 09:54:30 2024
$end
$version
	Icarus Verilog
$end
$timescale
	1ps
$end
$scope module seq_detect_mealy_tb $end
$var wire 1 ! o_out $end
$var reg 1 " i_clk $end
$var reg 1 # i_rstn $end
$var reg 1 $ i_seq $end
$var reg 256 % taskState [255:0] $end
$var reg 256 & vcd_file [255:0] $end
$var integer 32 ' i [31:0] $end
$scope module u_seq_detect_mealy $end
$var wire 1 " i_clk $end
$var wire 1 # i_rstn $end
$var wire 1 $ i_seq $end
$var reg 3 ( cState [2:0] $end
$var reg 3 ) nState [2:0] $end
$var reg 1 ! o_out $end
$var reg 1 * seq $end
$var reg 256 + stateMonitor [255:0] $end
$upscope $end
$scope task init $end
$upscope $end
$scope task resetNCycles $end
$var reg 10 , n [9:0] $end
$upscope $end
$upscope $end
$enddefinitions $end
#0
$dumpvars
b100 ,
b10100110101111101001001010001000100110001000101 +
0*
b0 )
b0 (
bx '
b10111000101111011101100110001101100100001011110111001101100101011100010101111101100100011001010111010001100101011000110111010001011111011011010110010101100001011011000111100100101110011101100110001101100100 &
b101001001100101011100110110010101110100010111110100111101001110 %
0$
0#
0"
0!
$end
#5000
1"
#10000
0"
#15000
1"
#20000
0"
#25000
1"
#30000
0"
#35000
1"
#40000
0"
1$
b0 '
b10100100110010101110011011001010111010001011111010011110100011001000110 %
1#
#45000
b1 )
1*
1"
#50000
0"
0$
b1 '
#55000
b10100110101111101001000 +
b10 )
0*
b1 (
1"
#60000
0"
b10 '
#65000
b1010011010111110100100001001100 +
b0 )
b10 (
1"
#70000
0"
b11 '
#75000
b10100110101111101001001010001000100110001000101 +
b0 (
1"
#80000
0"
1$
b100 '
#85000
b1 )
1*
1"
#90000
0"
b101 '
#95000
b10100110101111101001000 +
b1 (
1"
#100000
0"
0$
b110 '
#105000
b10 )
0*
1"
#110000
0"
b111 '
#115000
b1010011010111110100100001001100 +
b0 )
b10 (
1"
#120000
0"
1$
b1000 '
#125000
b10100110101111101001001010001000100110001000101 +
b1 )
1*
b0 (
1"
#130000
0"
b1001 '
#135000
b10100110101111101001000 +
b1 (
1"
#140000
0"
b1010 '
#145000
1"
#150000
0"
b1011 '
#155000
1"
#160000
0"
b1100 '
#165000
1"
#170000
0"
b1101 '
#175000
1"
#180000
0"
b1110 '
#185000
1"
#190000
0"
0$
b1111 '
#195000
b10 )
0*
1"
#200000
0"
b10000 '
#205000
b1010011010111110100100001001100 +
b0 )
b10 (
1"
#210000
0"
b10001 '
#215000
b10100110101111101001001010001000100110001000101 +
b0 (
1"
#220000
0"
1$
b10010 '
#225000
b1 )
1*
1"
#230000
0"
0$
b10011 '
#235000
b10100110101111101001000 +
b10 )
0*
b1 (
1"
#240000
0"
b10100 '
#245000
b1010011010111110100100001001100 +
b0 )
b10 (
1"
#250000
0"
1$
b10101 '
#255000
b10100110101111101001001010001000100110001000101 +
b1 )
1*
b0 (
1"
#260000
0"
b10110 '
#265000
b10100110101111101001000 +
b1 (
1"
#270000
0"
0$
b10111 '
#275000
b10 )
0*
1"
#280000
0"
b11000 '
#285000
b1010011010111110100100001001100 +
b0 )
b10 (
1"
#290000
0"
b11001 '
#295000
b10100110101111101001001010001000100110001000101 +
b0 (
1"
#300000
0"
1$
b11010 '
#305000
b1 )
1*
1"
#310000
0"
0$
b11011 '
#315000
b10100110101111101001000 +
b10 )
0*
b1 (
1"
#320000
0"
b11100 '
#325000
b1010011010111110100100001001100 +
b0 )
b10 (
1"
#330000
0"
b11101 '
#335000
b10100110101111101001001010001000100110001000101 +
b0 (
1"
#340000
0"
b11110 '
#345000
1"
#350000
0"
1$
b11111 '
#355000
b1 )
1*
1"
#360000
0"
0$
b100000 '
#365000
b10100110101111101001000 +
b10 )
0*
b1 (
1"
#370000
0"
1$
b100001 '
#375000
b1010011010111110100100001001100 +
b11 )
1*
b10 (
1"
#380000
0"
b100010 '
#385000
b101001101011111010010000100110001001000 +
1!
b1 )
b11 (
1"
#390000
0"
0$
b100011 '
#395000
b10100110101111101001000 +
0!
b10 )
0*
b1 (
1"
#400000
0"
b100100 '
#405000
b1010011010111110100100001001100 +
b0 )
b10 (
1"
#410000
0"
b100101 '
#415000
b10100110101111101001001010001000100110001000101 +
b0 (
1"
#420000
0"
b100110 '
#425000
1"
#430000
0"
b100111 '
#435000
1"
#440000
0"
1$
b101000 '
#445000
b1 )
1*
1"
#450000
0"
0$
b101001 '
#455000
b10100110101111101001000 +
b10 )
0*
b1 (
1"
#460000
0"
b101010 '
#465000
b1010011010111110100100001001100 +
b0 )
b10 (
1"
#470000
0"
b101011 '
#475000
b10100110101111101001001010001000100110001000101 +
b0 (
1"
#480000
0"
1$
b101100 '
#485000
b1 )
1*
1"
#490000
0"
0$
b101101 '
#495000
b10100110101111101001000 +
b10 )
0*
b1 (
1"
#500000
0"
1$
b101110 '
#505000
b1010011010111110100100001001100 +
b11 )
1*
b10 (
1"
#510000
0"
b101111 '
#515000
b101001101011111010010000100110001001000 +
1!
b1 )
b11 (
1"
#520000
0"
0$
b110000 '
#525000
b10100110101111101001000 +
0!
b10 )
0*
b1 (
1"
#530000
0"
b110001 '
#535000
b1010011010111110100100001001100 +
b0 )
b10 (
1"
#540000
0"
b110010 '
#545000
b10100110101111101001001010001000100110001000101 +
b0 (
1"
