project_0/05_fsm_traffic_light/fsm_traffic_light.v
// ==================================================
//	[ ZARAM OJT. ]
//	* Author		: Seok Jin Son (sonsj98@zaram.com)
//	* Filename		: fsm_traffic_light.v
//	* Date			: 2024-07-02 09:57:22
//	* Description	:
// ==================================================

module fsm_traffic_light 
(
	output	reg	[1:0]	o_LA,
	output	reg	[1:0]	o_LB,
	output	reg			o_M,
	input				i_TA,
	input				i_TB,
	input				i_P,
	input				i_R,
	input				i_clk,
	input				i_rstn
);

	reg	[2:0]	L_cState;
	reg	[2:0]	M_cState;
	reg	[1:0]	L_nState;
	reg	[1:0]	M_nState;


	//===================
	// (Mode FSM)
	//===================

	//States 
	localparam	MS0	=	2'b00;
    localparam	MS1 =	2'b01;

	//State Register
	always @(posedge i_clk or negedge i_rstn) begin
		if(!i_rstn) begin
			M_cState	<= MS0;
		end else begin
			M_cState	<= M_nState;
		end
	end

	//'Next State' Comb. logic
	always @(*) begin
		case (M_cState)
			MS0 : begin
				if (!i_P) begin
					M_nState = MS0;
				end else begin
					M_nState = MS1;
				end
			end
            MS1 : begin
				if (!i_R) begin
					M_nState = MS1;
				end else begin
					M_nState = MS0;
				end
			end
		endcase
	end



	//'Output' Comb. Logic
	always @(*) begin
		case(M_cState)
			MS0	: o_M = 1'b0;
			LS1	: o_M = 1'b1;
		endcase
	end

	//===================
	// (Lights FSM)
	//===================

	//States
	localparam	LS0	=	3'b000;
	localparam	LS1 =	3'b001;
	localparam	LS2 =	3'b010;
	localparam	LS3	=	3'b011;

	//Light outputs
	localparam	GREEN	= 2'b00;
	localparam	RED		= 2'b01;
	localparam	YELLOW	= 2'b10;

	//State Register
	always @(posedge i_clk or negedge i_rstn) begin
		if(!i_rstn) begin
			L_cState	<= LS0;
		end else begin
			L_cState	<= L_nState;
		end
	end

	//'Next State' Comb. logic
	always @(*) begin
		case (L_cState)
			LS0 : begin
				if (i_TA) begin
					L_nState = LS0;
				end else begin
					L_nState = LS1;
				end
			end
            LS1 : L_nState = LS2;
            LS2 : begin
				if (o_M | i_TB) begin
					L_nState = LS2;
				end else begin
					L_nState = LS3;
				end
			end
            LS3 : L_nState = LS0;
		endcase
	end


	//'Output' Comb. Logic
	always @(*) begin
		case(L_cState)
			LS0	:	begin
				o_LA = GREEN;
				o_LB = RED;
			end
			LS1	:	begin
				o_LA = YELLOW;
				o_LB = RED;
			end
			LS2	:	begin
				o_LA = RED;
				o_LB = GREEN;
			end
			LS3	:	begin
				o_LA = RED;
				o_LB = YELLOW;
			end
		endcase
	end


	//DEBUG
	`ifdef DEBUG
		reg [32*8-1:0]	L_stateMonitor;
		always @(*) begin
			case(L_cState)
			LS0:	L_stateMonitor	=	"LS0";
            LS1:	L_stateMonitor	=	"LS1";
            LS2:	L_stateMonitor	=	"LS2";
            LS3:	L_stateMonitor	=	"LS3";
			endcase
		end

		reg [32*8-1:0]	M_stateMonitor;
		always @(*) begin
			case(M_cState)
			MS0:	M_stateMonitor	=	"MS0";
            MS1:	M_stateMonitor	=	"MS1";
			endcase
		end

		reg [32*8-1:0]	o_LA_colorMonitor;
		always @(*) begin
			case(o_LA)
			GREEN	:	o_LA_colorMonitor	=	"GREEN";
            RED		:	o_LA_colorMonitor	=	"RED";
            YELLOW	:	o_LA_colorMonitor	=	"YELLOW";
			endcase
		end

		reg [32*8-1:0]	o_LB_colorMonitor;
		always @(*) begin
			case(o_LB)
			GREEN	:	o_LB_colorMonitor	=	"GREEN";
            RED		:	o_LB_colorMonitor	=	"RED";
            YELLOW	:	o_LB_colorMonitor	=	"YELLOW";
			endcase
		end
	`endif
	

endmodule

project_0/05_fsm_traffic_light/fsm_traffic_light_tb.v
// ==================================================
//	[ ZARAM OJT. ]
//	* Author		: Seok Jin Son (sonsj98@zaram.com)
//	* Filename		: fsm_traffic_light_tb.v
//	* Date			: 2024-07-02 11:39:35
//	* Description	:
// ==================================================

// --------------------------------------------------
//	Define Global Variables
// --------------------------------------------------
`define	CLKFREQ		100		// Clock Freq. (Unit: MHz)
`define	SIMCYCLE	50		// Sim. Cycles
`define DEBUG


// --------------------------------------------------
//	Includes
// --------------------------------------------------
`include	"fsm_traffic_light.v"

module fsm_traffic_light_tb;
// --------------------------------------------------
//	DUT Signals & Instantiate
// --------------------------------------------------
	wire		[1:0]	o_LA;
	wire		[1:0]	o_LB;
	wire				o_M;
	reg					i_TA;
	reg					i_TB;
	reg					i_P;
	reg					i_R;
	reg					i_clk;
	reg					i_rstn;

	fsm_traffic_light
	u_fsm_traffic_light(
	.o_LA				(o_LA				),
	.o_LB				(o_LB				),
	.o_M				(o_M				),
	.i_TA				(i_TA				),
	.i_TB				(i_TB				),
	.i_P				(i_P				),
	.i_R				(i_R				),
	.i_clk				(i_clk				),
	.i_rstn				(i_rstn				)
	);


// ----------------------------------
// Clock
// ----------------------------------
	always	#(500/`CLKFREQ) i_clk = ~ i_clk;

// ----------------------------------
// Tasks
// ----------------------------------
	reg [8*32-1:0] 	taskState;

	task init;
		begin
			taskState	= "Init";
			i_TA		= 0;
			i_TB		= 0;
			i_P			= 0;
			i_R			= 0;
			i_clk		= 0;
			i_rstn		= 0;
		end
	endtask

	task resetNCycle;
		input	[9:0]	n;
		begin
			taskState		= "Reset_ON";
			#(n*1000/`CLKFREQ);
			i_rstn = 1;
			taskState		= "Reset_OFF";
		end
	endtask


// --------------------------------------------------
//	Test Stimulus
// --------------------------------------------------
	integer		i, j;
	initial begin
		init();
		resetNCycle(4);

		for (i=0; i<`SIMCYCLE; i++) begin
			i_TA	= $urandom_range(0,1);
			i_TB	= $urandom_range(0,1);
			i_P		= $urandom_range(0,1);
			i_R		= $urandom_range(0,1);
			#(1000/`CLKFREQ);
		end
		$finish;
	end

// --------------------------------------------------
//	Dump VCD
// --------------------------------------------------
	reg	[8*32-1:0]	vcd_file;
	initial begin
		if ($value$plusargs("vcd_file=%s", vcd_file)) begin
			$dumpfile(vcd_file);
			$dumpvars;
		end else begin
			$dumpfile("fsm_traffic_light_tb.vcd");
			$dumpvars;
		end
	end

endmodule

project_0/05_fsm_traffic_light/vcd/fsm_traffic_light.vcd
$date
	Wed Jul  3 13:45:33 2024
$end
$version
	Icarus Verilog
$end
$timescale
	1ps
$end
$scope module fsm_traffic_light_tb $end
$var wire 1 ! o_M $end
$var wire 2 " o_LB [1:0] $end
$var wire 2 # o_LA [1:0] $end
$var reg 1 $ i_P $end
$var reg 1 % i_R $end
$var reg 1 & i_TA $end
$var reg 1 ' i_TB $end
$var reg 1 ( i_clk $end
$var reg 1 ) i_rstn $end
$var reg 256 * taskState [255:0] $end
$var reg 256 + vcd_file [255:0] $end
$var integer 32 , i [31:0] $end
$scope module u_fsm_traffic_light $end
$var wire 1 $ i_P $end
$var wire 1 % i_R $end
$var wire 1 & i_TA $end
$var wire 1 ' i_TB $end
$var wire 1 ( i_clk $end
$var wire 1 ) i_rstn $end
$var reg 3 - L_cState [2:0] $end
$var reg 2 . L_nState [1:0] $end
$var reg 256 / L_stateMonitor [255:0] $end
$var reg 3 0 M_cState [2:0] $end
$var reg 2 1 M_nState [1:0] $end
$var reg 256 2 M_stateMonitor [255:0] $end
$var reg 2 3 o_LA [1:0] $end
$var reg 256 4 o_LA_colorMonitor [255:0] $end
$var reg 2 5 o_LB [1:0] $end
$var reg 256 6 o_LB_colorMonitor [255:0] $end
$var reg 1 ! o_M $end
$upscope $end
$scope task init $end
$upscope $end
$scope task resetNCycle $end
$var reg 10 7 n [9:0] $end
$upscope $end
$upscope $end
$enddefinitions $end
#0
$dumpvars
b100 7
b10100100100010101000100 6
b1 5
b100011101010010010001010100010101001110 4
b0 3
b10011010101001100110000 2
b0 1
b0 0
b10011000101001100110000 /
b1 .
b0 -
bx ,
b1011100010111101110110011000110110010000101111011001100111001101101101010111110111010001110010011000010110011001100110011010010110001101011111011011000110100101100111011010000111010000101110011101100110001101100100 +
b101001001100101011100110110010101110100010111110100111101001110 *
0)
0(
0'
0&
0%
0$
b0 #
b1 "
0!
$end
#5000
1(
#10000
0(
#15000
1(
#20000
0(
#25000
1(
#30000
0(
#35000
1(
#40000
b0 .
0(
1&
b0 ,
b10100100110010101110011011001010111010001011111010011110100011001000110 *
1)
#45000
1(
#50000
0(
1'
b1 ,
#55000
1(
#60000
b1 1
0(
1%
1$
b10 ,
#65000
1!
b10011010101001100110001 2
b0 1
b1 0
1(
#70000
b1 1
0(
0%
b11 ,
#75000
1(
#80000
b1 .
0(
0'
0&
b100 ,
#85000
b10110010100010101001100010011000100111101010111 4
b10 #
b10 3
b10011000101001100110001 /
b10 .
b1 -
1(
#90000
0(
1'
b101 ,
#95000
b100011101010010010001010100010101001110 6
b10100100100010101000100 4
b10011000101001100110010 /
b0 "
b0 5
b1 #
b1 3
b10 -
1(
#100000
0(
0'
b110 ,
#105000
1(
#110000
b0 1
0(
1%
0$
b111 ,
#115000
b11 .
b10011010101001100110000 2
0!
b0 0
1(
#120000
b1 1
b10 .
0(
0%
1$
1'
b1000 ,
#125000
1!
b10011010101001100110001 2
b1 0
1(
#130000
0(
0$
0'
b1001 ,
#135000
1(
#140000
0(
1&
b1010 ,
#145000
1(
#150000
b0 1
0(
1%
1$
b1011 ,
#155000
b11 .
b10011010101001100110000 2
0!
b1 1
b0 0
1(
#160000
0(
0&
b1100 ,
#165000
b10110010100010101001100010011000100111101010111 6
b10 "
b10 5
b10011000101001100110011 /
b0 .
1!
b10011010101001100110001 2
b0 1
b11 -
b1 0
1(
#170000
b1 1
0(
0%
1&
b1101 ,
#175000
b10100100100010101000100 6
b100011101010010010001010100010101001110 4
b10011000101001100110000 /
b1 "
b1 5
b0 #
b0 3
b0 -
1(
#180000
b0 1
0(
1%
1'
b1110 ,
#185000
b10011010101001100110000 2
0!
b1 1
b0 0
1(
#190000
b0 1
b1 .
0(
0%
0$
0&
b1111 ,
#195000
b10110010100010101001100010011000100111101010111 4
b10 #
b10 3
b10011000101001100110001 /
b10 .
b1 -
1(
#200000
0(
1%
1&
b10000 ,
#205000
b100011101010010010001010100010101001110 6
b10100100100010101000100 4
b10011000101001100110010 /
b0 "
b0 5
b1 #
b1 3
b10 -
1(
#210000
b1 1
0(
1$
0&
b10001 ,
#215000
1!
b10011010101001100110001 2
b0 1
b1 0
1(
#220000
0(
1&
b10010 ,
#225000
b10011010101001100110000 2
0!
b1 1
b0 0
1(
#230000
b0 1
b11 .
0(
0%
0$
0'
b10011 ,
#235000
b10110010100010101001100010011000100111101010111 6
b10 "
b10 5
b10011000101001100110011 /
b0 .
b11 -
1(
#240000
0(
1'
0&
b10100 ,
#245000
b10100100100010101000100 6
b100011101010010010001010100010101001110 4
b10011000101001100110000 /
b1 "
b1 5
b0 #
b0 3
b1 .
b0 -
1(
#250000
b1 1
0(
1%
1$
0'
b10101 ,
#255000
b10110010100010101001100010011000100111101010111 4
1!
b10011010101001100110001 2
b0 1
b10 #
b10 3
b10011000101001100110001 /
b10 .
b1 0
b1 -
1(
#260000
0(
0$
1'
b10110 ,
#265000
b100011101010010010001010100010101001110 6
b10100100100010101000100 4
b10011000101001100110010 /
b0 "
b0 5
b1 #
b1 3
b10011010101001100110000 2
0!
b10 -
b0 0
1(
#270000
b1 1
b11 .
0(
1$
0'
1&
b10111 ,
#275000
b10110010100010101001100010011000100111101010111 6
1!
b10011010101001100110001 2
b0 1
b10 "
b10 5
b10011000101001100110011 /
b0 .
b1 0
b11 -
1(
#280000
b1 1
0(
0%
b11000 ,
#285000
b10100100100010101000100 6
b100011101010010010001010100010101001110 4
b10011000101001100110000 /
b1 "
b1 5
b0 #
b0 3
b0 -
1(
#290000
b0 1
0(
1%
0$
1'
b11001 ,
#295000
b10011010101001100110000 2
0!
b0 0
1(
#300000
0(
0%
0'
b11010 ,
#305000
1(
#310000
b1 1
0(
1$
b11011 ,
#315000
1!
b10011010101001100110001 2
b1 0
1(
#320000
b0 1
b1 .
0(
1%
0$
0&
b11100 ,
#325000
b10110010100010101001100010011000100111101010111 4
b10 #
b10 3
b10011000101001100110001 /
b10 .
b10011010101001100110000 2
0!
b1 -
b0 0
1(
#330000
0(
1&
b11101 ,
#335000
b100011101010010010001010100010101001110 6
b10100100100010101000100 4
b10011000101001100110010 /
b0 "
b0 5
b1 #
b1 3
b11 .
b10 -
1(
#340000
0(
0%
b11110 ,
#345000
b10110010100010101001100010011000100111101010111 6
b10 "
b10 5
b10011000101001100110011 /
b0 .
b11 -
1(
#350000
b1 1
0(
1%
1$
0&
b11111 ,
#355000
b10100100100010101000100 6
b100011101010010010001010100010101001110 4
1!
b10011010101001100110001 2
b0 1
b10011000101001100110000 /
b1 "
b1 5
b0 #
b0 3
b1 .
b1 0
b0 -
1(
#360000
0(
1'
b100000 ,
#365000
b10110010100010101001100010011000100111101010111 4
b10 #
b10 3
b10011000101001100110001 /
b10 .
b10011010101001100110000 2
0!
b1 1
b1 -
b0 0
1(
#370000
b0 1
0(
0%
0$
0'
1&
b100001 ,
#375000
b100011101010010010001010100010101001110 6
b10100100100010101000100 4
b10011000101001100110010 /
b0 "
b0 5
b1 #
b1 3
b11 .
b10 -
1(
#380000
b10 .
0(
1'
b100010 ,
#385000
1(
#390000
b1 1
b11 .
0(
1$
0'
b100011 ,
#395000
b10110010100010101001100010011000100111101010111 6
1!
b10011010101001100110001 2
b10 "
b10 5
b10011000101001100110011 /
b0 .
b1 0
b11 -
1(
#400000
0(
0$
1'
b100100 ,
#405000
b10100100100010101000100 6
b100011101010010010001010100010101001110 4
b10011000101001100110000 /
b1 "
b1 5
b0 #
b0 3
b0 -
1(
#410000
0(
1$
0'
b100101 ,
#415000
1(
#420000
b0 1
b1 .
0(
1%
1'
0&
b100110 ,
#425000
b10110010100010101001100010011000100111101010111 4
b10 #
b10 3
b10011000101001100110001 /
b10 .
b10011010101001100110000 2
0!
b1 1
b1 -
b0 0
1(
#430000
0(
b100111 ,
#435000
b100011101010010010001010100010101001110 6
b10100100100010101000100 4
1!
b10011010101001100110001 2
b0 1
b10011000101001100110010 /
b0 "
b0 5
b1 #
b1 3
b1 0
b10 -
1(
#440000
b1 1
0(
0%
b101000 ,
#445000
1(
#450000
b0 1
0(
1%
0$
0'
b101001 ,
#455000
b11 .
b10011010101001100110000 2
0!
b0 0
1(
#460000
b10 .
0(
1'
b101010 ,
#465000
1(
#470000
b1 1
b11 .
0(
0%
1$
0'
b101011 ,
#475000
b10110010100010101001100010011000100111101010111 6
1!
b10011010101001100110001 2
b10 "
b10 5
b10011000101001100110011 /
b0 .
b1 0
b11 -
1(
#480000
b0 1
0(
1%
1'
b101100 ,
#485000
b10100100100010101000100 6
b100011101010010010001010100010101001110 4
b10011000101001100110000 /
b1 "
b1 5
b0 #
b0 3
b1 .
b10011010101001100110000 2
0!
b1 1
b0 -
b0 0
1(
#490000
b0 1
b0 .
0(
0$
0'
1&
b101101 ,
#495000
1(
#500000
b1 1
0(
0%
1$
1'
b101110 ,
#505000
1!
b10011010101001100110001 2
b1 0
1(
#510000
b0 1
0(
1%
b101111 ,
#515000
b10011010101001100110000 2
0!
b1 1
b0 0
1(
#520000
b0 1
0(
0$
0'
b110000 ,
#525000
1(
#530000
b1 1
b1 .
0(
0%
1$
0&
b110001 ,
#535000
b10110010100010101001100010011000100111101010111 4
1!
b10011010101001100110001 2
b10 #
b10 3
b10011000101001100110001 /
b10 .
b1 0
b1 -
1(
#540000
0(
b110010 ,
