project_0/02_alu/alu.v
// ==================================================
//	[ ZARAM OJT. ]
//	* Author		: Seok Jin Son (sonsj98@zaram.com)
//	* Filename		: alu.v
//	* Date			: 2024-07-01 15:36:05
//	* Description	:
// ==================================================

module alu 
#(
	parameter BW_DATA = 4
)
(
	output	reg	[BW_DATA-1:0]	o_Y,
	output	reg					o_Cout,
	input		[BW_DATA-1:0]	i_A,
	input		[BW_DATA-1:0]	i_B,
	input		[2:0]			i_F
);
	

	always @ (*) begin
		o_Cout	= 0;
		case (i_F)
			3'b000 	: o_Y			= i_A & i_B;
			3'b001 	: o_Y 			= i_A | i_B;
			3'b010 	: {o_Cout, o_Y} = i_A + i_B;
			3'b011 	: o_Y 			= 0;
			3'b100 	: o_Y 			= i_A & ~i_B;
			3'b101 	: o_Y 			= i_A | ~i_B;
			3'b110 	: o_Y			= i_A - i_B;
			3'b111 	: o_Y			= (i_A < i_B) ? 1 : 0;
			default : o_Y			= 0;
		endcase
	end


endmodule

project_0/02_alu/alu_tb.v
// ==================================================
//	[ ZARAM OJT. ]
//	* Author		: Seok Jin Son (sonsj98@zaram.com)
//	* Filename		: alu_tb.v
//	* Date			: 2024-07-01 15:50:14
//	* Description	:
// ==================================================

// --------------------------------------------------
//	Define Global Variables
// --------------------------------------------------
`define	CLKFREQ		100		// Clock Freq. (Unit: MHz)
`define	SIMCYCLE	5		// Sim. Cycles
`define BW_DATA		4

// --------------------------------------------------
//	Includes
// --------------------------------------------------
`include	"alu.v"

module alu_tb;
// --------------------------------------------------
//	DUT Signals & Instantiate
// --------------------------------------------------
	wire	[`BW_DATA-1:0]	o_Y;
	wire					o_Cout;
	reg		[`BW_DATA-1:0]	i_A;
	reg		[`BW_DATA-1:0]	i_B;
	reg		[2:0]			i_F;

	alu
	#(
	.BW_DATA			(`BW_DATA			)
	)
	u_alu(
	.o_Y				(o_Y				),
	.o_Cout				(o_Cout				),
	.i_A				(i_A				),
	.i_B				(i_B				),
	.i_F				(i_F				)
	);



// ----------------------------------
// Tasks
// ----------------------------------
	reg [8*32-1:0] 	taskState;

	task init;
		begin
			taskState	= "Init";
			i_A  		= 0;
			i_B  		= 0;
			i_F			= 0;
		end
	endtask

// --------------------------------------------------
//	Test Stimulus
// --------------------------------------------------
	integer		i, j;
	initial begin
		init();

		for (i=0; i<`SIMCYCLE; i++) begin
			#(1000/`CLKFREQ);
			taskState	= "A & B";
            i_F	= 3'b000;
			i_A	= $urandom;
            i_B	= $urandom;
		end

		for (i=0; i<`SIMCYCLE; i++) begin
			#(1000/`CLKFREQ);
			taskState	= "A | B";
            i_F	= 3'b001;
			i_A	= $urandom;
            i_B	= $urandom;
		end

		for (i=0; i<`SIMCYCLE; i++) begin
			#(1000/`CLKFREQ);
			taskState	= "A + B";
            i_F	= 3'b010;
			i_A	= $urandom;
            i_B	= $urandom;
		end

		for (i=0; i<`SIMCYCLE; i++) begin
			#(1000/`CLKFREQ);
			taskState	= "not used";
            i_F	= 3'b011;
			i_A	= $urandom;
            i_B	= $urandom;
		end

		for (i=0; i<`SIMCYCLE; i++) begin
			#(1000/`CLKFREQ);
			taskState	= "A & ~B";
            i_F	= 3'b100;
			i_A	= $urandom;
            i_B	= $urandom;
		end

		for (i=0; i<`SIMCYCLE; i++) begin
			#(1000/`CLKFREQ);
			taskState	= "A | ~B";
            i_F	= 3'b101;
			i_A	= $urandom;
            i_B	= $urandom;
		end

		for (i=0; i<`SIMCYCLE; i++) begin
			#(1000/`CLKFREQ);
			taskState	= "A - B";
            i_F	= 3'b110;
			i_A	= $urandom;
            i_B	= $urandom;
		end

		for (i=0; i<`SIMCYCLE; i++) begin
			#(1000/`CLKFREQ);
			taskState	= "SLT";
            i_F	= 3'b111;
			i_A	= $urandom;
            i_B	= $urandom;
		end

		$finish;
	end

// --------------------------------------------------
//	Dump VCD
// --------------------------------------------------
	reg	[8*32-1:0]	vcd_file;
	initial begin
		if ($value$plusargs("vcd_file=%s", vcd_file)) begin
			$dumpfile(vcd_file);
			$dumpvars;
		end else begin
			$dumpfile("alu_tb.vcd");
			$dumpvars;
		end
	end

endmodule

project_0/02_alu/vcd/alu.vcd
$date
	Tue Jul  2 09:50:49 2024
$end
$version
	Icarus Verilog
$end
$timescale
	1ps
$end
$scope module alu_tb $end
$var wire 4 ! o_Y [3:0] $end
$var wire 1 " o_Cout $end
$var reg 4 # i_A [3:0] $end
$var reg 4 $ i_B [3:0] $end
$var reg 3 % i_F [2:0] $end
$var reg 256 & taskState [255:0] $end
$var reg 256 ' vcd_file [255:0] $end
$var integer 32 ( i [31:0] $end
$scope module u_alu $end
$var wire 4 ) i_A [3:0] $end
$var wire 4 * i_B [3:0] $end
$var wire 3 + i_F [2:0] $end
$var reg 1 " o_Cout $end
$var reg 4 , o_Y [3:0] $end
$upscope $end
$scope task init $end
$upscope $end
$upscope $end
$enddefinitions $end
#0
$dumpvars
b0 ,
b0 +
b0 *
b0 )
b0 (
b101110001011110111011001100011011001000010111101100001011011000111010100101110011101100110001101100100 '
b1001001011011100110100101110100 &
b0 %
b0 $
b0 #
0"
b0 !
$end
#10000
b1 (
b1 $
b1 *
b100 #
b100 )
b100000100100000001001100010000001000010 &
#20000
b1 !
b1 ,
b10 (
b11 $
b11 *
b1001 #
b1001 )
#30000
b1101 !
b1101 ,
b11 (
b1101 $
b1101 *
b1101 #
b1101 )
#40000
b0 !
b0 ,
b100 (
b10 $
b10 *
b101 #
b101 )
#50000
b1 !
b1 ,
b0 (
b1101 $
b1101 *
b1 #
b1 )
#60000
b1111 !
b1111 ,
b1 (
b110 #
b110 )
b1 %
b1 +
b100000100100000011111000010000001000010 &
#70000
b1101 !
b1101 ,
b10 (
b1100 $
b1100 *
b1101 #
b1101 )
#80000
b1111 !
b1111 ,
b11 (
b110 $
b110 *
b1001 #
b1001 )
#90000
b100 (
b1010 $
b1010 *
b101 #
b101 )
#100000
b111 !
b111 ,
b0 (
b111 $
b111 *
#110000
1"
b1 !
b1 ,
b1 (
b1111 $
b1111 *
b10 #
b10 )
b10 %
b10 +
b100000100100000001010110010000001000010 &
#120000
b0 !
b0 ,
1"
b10 (
b1110 $
b1110 *
#130000
b1101 !
b1101 ,
0"
b11 (
b101 $
b101 *
b1000 #
b1000 )
#140000
1"
b1001 !
b1001 ,
b100 (
b1101 $
b1101 *
b1100 #
b1100 )
#150000
b10 !
b10 ,
1"
b0 (
b101 $
b101 *
b1101 #
b1101 )
#160000
b0 !
b0 ,
0"
b1 (
b1010 $
b1010 *
b11 #
b11 )
b11 %
b11 +
b110111001101111011101000010000001110101011100110110010101100100 &
#170000
b10 (
b0 $
b0 *
b0 #
b0 )
#180000
b11 (
b1101 $
b1101 *
b1010 #
b1010 )
#190000
b100 (
b11 $
b11 *
b110 #
b110 )
#200000
b0 (
b1101 #
b1101 )
#210000
b1010 !
b1010 ,
b1 (
b101 $
b101 *
b1011 #
b1011 )
b100 %
b100 +
b10000010010000000100110001000000111111001000010 &
#220000
b0 !
b0 ,
b10 (
b1110 $
b1110 *
b10 #
b10 )
#230000
b11 (
b1111 $
b1111 *
b1101 #
b1101 )
#240000
b1 !
b1 ,
b100 (
b1010 $
b1010 *
b11 #
b11 )
#250000
b10 !
b10 ,
b0 (
b1100 $
b1100 *
b1010 #
b1010 )
#260000
b111 !
b111 ,
b1 (
b1010 $
b1010 *
b10 #
b10 )
b101 %
b101 +
b10000010010000001111100001000000111111001000010 &
#270000
b10 (
b1000 $
b1000 *
b1 #
b1 )
#280000
b1110 !
b1110 ,
b11 (
b1001 $
b1001 *
b1000 #
b1000 )
#290000
b1011 !
b1011 ,
b100 (
b110 $
b110 *
b1011 #
b1011 )
#300000
b111 !
b111 ,
b0 (
b1110 $
b1110 *
b110 #
b110 )
#310000
b10 !
b10 ,
b1 (
b1010 $
b1010 *
b1100 #
b1100 )
b110 %
b110 +
b100000100100000001011010010000001000010 &
#320000
b1010 !
b1010 ,
b10 (
b1 $
b1 *
b1011 #
b1011 )
#330000
b110 !
b110 ,
b11 (
b1111 $
b1111 *
b101 #
b101 )
#340000
b1 !
b1 ,
b100 (
b1010 $
b1010 *
b1011 #
b1011 )
#350000
b1001 !
b1001 ,
b0 (
b101 $
b101 *
b1110 #
b1110 )
#360000
b1 !
b1 ,
b1 (
b1001 $
b1001 *
b1 #
b1 )
b111 %
b111 +
b10100110100110001010100 &
#370000
b10 (
b1100 $
b1100 *
b10 #
b10 )
#380000
b0 !
b0 ,
b11 (
b1111 $
b1111 *
b1111 #
b1111 )
#390000
b100 (
b111 $
b111 *
b1000 #
b1000 )
#400000
b101 (
b1100 $
b1100 *
b1111 #
b1111 )
