project_0/06_sram_extension/spsram.v
// ==================================================
//	[ ZARAM OJT. ]
//	* Author		: Seok Jin Son (sonsj98@zaram.com)
//	* Filename		: spsram.v
//	* Date			: 2024-06-26 14:26:32
//	* Description	:
// ==================================================

module spsram 
#(
	parameter	BW_DATA	=	32,
	parameter	BW_ADDR	=	4
)
(
	output	[BW_DATA-1:0]	o_data,
	input	[BW_DATA-1:0]	i_data,
	input	[BW_ADDR-1:0]	i_addr,
	input					i_wen,
	input					i_cen,
	input					i_oen,
	input					i_clk
);
	
	//Memory Write
	reg	[BW_DATA-1:0]	mem[0:2**BW_ADDR-1];
	always @(posedge i_clk) begin
		if(i_cen && i_wen) begin
			mem[i_addr]	<=	i_data;
		end else begin
			mem[i_addr] <= mem[i_addr];
		end
	end


	//Memory Read
	`ifdef	SPSRAM_ASYNC
		assign	o_data	=	!i_oen	?	'bz	:
							i_cen	&&	!i_wen	?	mem[i_addr]	:	'bx;

	`else
		reg	[BW_DATA-1:0]	o_data;
		always @(posedge i_clk) begin
			if(i_oen) begin
				if(i_cen && !i_wen) begin
					o_data	<=	mem[i_addr];
				end	else begin
					o_data	<=	'bx;
				end
			end else begin
				o_data	<= 'bz;
			end
		end
	`endif

endmodule

project_0/06_sram_extension/sram_extension.v
// ==================================================
//	[ ZARAM OJT. ]
//	* Author		: Seok Jin Son (sonsj98@zaram.com)
//	* Filename		: sram_extension.v
//	* Date			: 2024-07-02 13:44:12
//	* Description	:
// ==================================================

`include	"spsram.v"

module sram_extension
#(
	parameter	BW_DATA	=	64,
	parameter	BW_ADDR	=	6
)
(
	output	[BW_DATA-1:0]	o_data,
	input	[BW_DATA-1:0]	i_data,
	input	[BW_ADDR-1:0]	i_addr,
	input					i_wen,
	input					i_cen,
	input					i_oen,
	input					i_clk
);
	

	spsram
	#(
	.BW_DATA			(32			),
	.BW_ADDR			(4			)
	)
	u_spsram_0(
	.o_data				(o_data[32-1:0]			),
	.i_data				(i_data[32-1:0]			),
	.i_addr				(i_addr[3:0]			),
	.i_wen				(i_wen					),
	.i_cen				(~i_addr[5] & ~i_addr[4]),
	.i_oen				(~i_addr[5]	& ~i_addr[4]),
	.i_clk				(i_clk					)
	);


	spsram
	#(
	.BW_DATA			(32			),
	.BW_ADDR			(4			)
	)	
	u_spsram_1(
	.o_data				(o_data[32-1:0]			),
	.i_data				(i_data[32-1:0]			),
	.i_addr				(i_addr[3:0]			),
	.i_wen				(i_wen					),
	.i_cen				(~i_addr[5] & i_addr[4]	),
	.i_oen				(~i_addr[5]	& i_addr[4]	),
	.i_clk				(i_clk					)
	);

	spsram
	#(
	.BW_DATA			(32			),
	.BW_ADDR			(4			)
	)	
	u_spsram_2(
	.o_data				(o_data[32-1:0]			),
	.i_data				(i_data[32-1:0]			),
	.i_addr				(i_addr[3:0]			),
	.i_wen				(i_wen					),
	.i_cen				(i_addr[5] & ~i_addr[4]	),
	.i_oen				(i_addr[5] & ~i_addr[4]	),
	.i_clk				(i_clk					)
	);

	spsram
	#(
	.BW_DATA			(32			),
	.BW_ADDR			(4			)
	)	
	u_spsram_3(
	.o_data				(o_data[32-1:0]			),
	.i_data				(i_data[32-1:0]			),
	.i_addr				(i_addr[3:0]			),
	.i_wen				(i_wen					),
	.i_cen				(i_addr[5] & i_addr[4]	),
	.i_oen				(i_addr[5] & i_addr[4]	),
	.i_clk				(i_clk					)
	);

	spsram
	#(
	.BW_DATA			(32			),
	.BW_ADDR			(4			)
	)
	u_spsram_4(
	.o_data				(o_data[64-1:32]		),
	.i_data				(i_data[64-1:32]		),
	.i_addr				(i_addr[3:0]			),
	.i_wen				(i_wen					),
	.i_cen				(~i_addr[5] & ~i_addr[4]),
	.i_oen				(~i_addr[5]	& ~i_addr[4]),
	.i_clk				(i_clk					)
	);


	spsram
	#(
	.BW_DATA			(32			),
	.BW_ADDR			(4			)
	)	
	u_spsram_5(
	.o_data				(o_data[64-1:32]		),
	.i_data				(i_data[64-1:32]		),
	.i_addr				(i_addr[3:0]			),
	.i_wen				(i_wen					),
	.i_cen				(~i_addr[5] & i_addr[4]	),
	.i_oen				(~i_addr[5]	& i_addr[4]	),
	.i_clk				(i_clk					)
	);

	spsram
	#(
	.BW_DATA			(32			),
	.BW_ADDR			(4			)
	)	
	u_spsram_6(
	.o_data				(o_data[64-1:32]		),
	.i_data				(i_data[64-1:32]		),
	.i_addr				(i_addr[3:0]			),
	.i_wen				(i_wen					),
	.i_cen				(i_addr[5] & ~i_addr[4]	),
	.i_oen				(i_addr[5] & ~i_addr[4]	),
	.i_clk				(i_clk					)
	);

	spsram
	#(
	.BW_DATA			(32			),
	.BW_ADDR			(4			)
	)	
	u_spsram_7(
	.o_data				(o_data[64-1:32]		),
	.i_data				(i_data[64-1:32]		),
	.i_addr				(i_addr[3:0]			),
	.i_wen				(i_wen					),
	.i_cen				(i_addr[5] & i_addr[4]	),
	.i_oen				(i_addr[5] & i_addr[4]	),
	.i_clk				(i_clk					)
	);


endmodule

project_0/06_sram_extension/sram_extension_tb.v
// ==================================================
//	[ ZARAM OJT. ]
//	* Author		: Seok Jin Son (sonsj98@zaram.com)
//	* Filename		: sram_extension_tb.v
//	* Date			: 2024-07-02 13:55:31
//	* Description	:
// ==================================================

// --------------------------------------------------
//	Define Global Variables
// --------------------------------------------------
`define	CLKFREQ		100		// Clock Freq. (Unit: MHz)
`define	SIMCYCLE	64		// Sim. Cycles
`define BW_DATA		64		// Bitwidth of ~~
`define BW_ADDR		6		// Bitwidth of ~~

// --------------------------------------------------
//	Includes
// --------------------------------------------------
`include	"sram_extension.v"

module sram_extension_tb;
// --------------------------------------------------
//	DUT Signals & Instantiate
// --------------------------------------------------
	wire	[`BW_DATA-1:0]	o_data;
	reg		[`BW_DATA-1:0]	i_data;
	reg		[`BW_ADDR-1:0]	i_addr;
	reg						i_wen;
	reg						i_cen;
	reg						i_oen;
	reg						i_clk;

	sram_extension
	#(
	.BW_DATA			(`BW_DATA			),
	.BW_ADDR			(`BW_ADDR			)
	)
	u_sram_extension(
	.o_data				(o_data				),
	.i_data				(i_data				),
	.i_addr				(i_addr				),
	.i_wen				(i_wen				),
	.i_cen				(i_cen				),
	.i_oen				(i_oen				),
	.i_clk				(i_clk				)
	);

// ----------------------------------
// Clock
// ----------------------------------
	always	#(500/`CLKFREQ) i_clk = ~ i_clk;


// ----------------------------------
// Tasks
// ----------------------------------
	reg [8*32-1:0] 	taskState;

	task init;
		begin
			taskState	= "Init";
			i_data  	= 0;
            i_addr  	= 0;
            i_wen		= 0;
            i_cen		= 0;
            i_oen		= 0;
            i_clk		= 0;
		end
	endtask

	task memWR;
		input	[`BW_ADDR-1:0]	ti_addr;
		input	[`BW_DATA-1:0]	ti_data;
		begin
			@(negedge i_clk) begin
				taskState	= "WR";
				i_addr		= ti_addr;
				i_data		= ti_data;
				i_wen		= 1;
				i_cen		= 1;
				i_oen		= 0;
			end
		end
	endtask

	task memRD;
		input	[`BW_ADDR-1:0] ti_addr;
		begin
			@(negedge i_clk) begin
				taskState	= "RD";
				i_addr		= ti_addr;
				i_wen		= 0;
				i_cen		= 1;
				i_oen		= 1;
			end
		end
	endtask



// --------------------------------------------------
//	Test Stimulus
// --------------------------------------------------
	integer		i, j;
	initial begin
		init();
		#(4*1000/`CLKFREQ);

		for (i=0; i<`SIMCYCLE; i++) begin
			j = $urandom;
			memWR(i, j);
		end
		for (i=0; i<`SIMCYCLE; i++) begin
			memRD(i);
		end
		$finish;
	end


// --------------------------------------------------
//	Dump VCD
// --------------------------------------------------
	reg	[8*32-1:0]	vcd_file;
	initial begin
		if ($value$plusargs("vcd_file=%s", vcd_file)) begin
			$dumpfile(vcd_file);
			$dumpvars;
		end else begin
			$dumpfile("sram_extension_tb.vcd");
			$dumpvars;
		end
	end

endmodule

project_0/06_sram_extension/vcd/sram_extension.vcd
$date
	Tue Jul  2 18:16:21 2024
$end
$version
	Icarus Verilog
$end
$timescale
	1ps
$end
$scope module sram_extension_tb $end
$var wire 64 ! o_data [63:0] $end
$var reg 6 " i_addr [5:0] $end
$var reg 1 # i_cen $end
$var reg 1 $ i_clk $end
$var reg 64 % i_data [63:0] $end
$var reg 1 & i_oen $end
$var reg 1 ' i_wen $end
$var reg 256 ( taskState [255:0] $end
$var reg 256 ) vcd_file [255:0] $end
$var integer 32 * i [31:0] $end
$var integer 32 + j [31:0] $end
$scope module u_sram_extension $end
$var wire 6 , i_addr [5:0] $end
$var wire 1 # i_cen $end
$var wire 1 $ i_clk $end
$var wire 64 - i_data [63:0] $end
$var wire 1 & i_oen $end
$var wire 1 ' i_wen $end
$var wire 64 . o_data [63:0] $end
$scope module u_spsram_0 $end
$var wire 4 / i_addr [3:0] $end
$var wire 1 0 i_cen $end
$var wire 1 $ i_clk $end
$var wire 32 1 i_data [31:0] $end
$var wire 1 2 i_oen $end
$var wire 1 ' i_wen $end
$var reg 32 3 o_data [31:0] $end
$upscope $end
$scope module u_spsram_1 $end
$var wire 4 4 i_addr [3:0] $end
$var wire 1 5 i_cen $end
$var wire 1 $ i_clk $end
$var wire 32 6 i_data [31:0] $end
$var wire 1 7 i_oen $end
$var wire 1 ' i_wen $end
$var reg 32 8 o_data [31:0] $end
$upscope $end
$scope module u_spsram_2 $end
$var wire 4 9 i_addr [3:0] $end
$var wire 1 : i_cen $end
$var wire 1 $ i_clk $end
$var wire 32 ; i_data [31:0] $end
$var wire 1 < i_oen $end
$var wire 1 ' i_wen $end
$var reg 32 = o_data [31:0] $end
$upscope $end
$scope module u_spsram_3 $end
$var wire 4 > i_addr [3:0] $end
$var wire 1 ? i_cen $end
$var wire 1 $ i_clk $end
$var wire 32 @ i_data [31:0] $end
$var wire 1 A i_oen $end
$var wire 1 ' i_wen $end
$var reg 32 B o_data [31:0] $end
$upscope $end
$scope module u_spsram_4 $end
$var wire 4 C i_addr [3:0] $end
$var wire 1 D i_cen $end
$var wire 1 $ i_clk $end
$var wire 32 E i_data [31:0] $end
$var wire 1 F i_oen $end
$var wire 1 ' i_wen $end
$var reg 32 G o_data [31:0] $end
$upscope $end
$scope module u_spsram_5 $end
$var wire 4 H i_addr [3:0] $end
$var wire 1 I i_cen $end
$var wire 1 $ i_clk $end
$var wire 32 J i_data [31:0] $end
$var wire 1 K i_oen $end
$var wire 1 ' i_wen $end
$var reg 32 L o_data [31:0] $end
$upscope $end
$scope module u_spsram_6 $end
$var wire 4 M i_addr [3:0] $end
$var wire 1 N i_cen $end
$var wire 1 $ i_clk $end
$var wire 32 O i_data [31:0] $end
$var wire 1 P i_oen $end
$var wire 1 ' i_wen $end
$var reg 32 Q o_data [31:0] $end
$upscope $end
$scope module u_spsram_7 $end
$var wire 4 R i_addr [3:0] $end
$var wire 1 S i_cen $end
$var wire 1 $ i_clk $end
$var wire 32 T i_data [31:0] $end
$var wire 1 U i_oen $end
$var wire 1 ' i_wen $end
$var reg 32 V o_data [31:0] $end
$upscope $end
$upscope $end
$scope task init $end
$upscope $end
$scope task memRD $end
$var reg 6 W ti_addr [5:0] $end
$upscope $end
$scope task memWR $end
$var reg 6 X ti_addr [5:0] $end
$var reg 64 Y ti_data [63:0] $end
$upscope $end
$upscope $end
$enddefinitions $end
#0
$dumpvars
bx Y
bx X
bx W
bx V
0U
b0 T
0S
b0 R
bx Q
0P
b0 O
0N
b0 M
bx L
0K
b0 J
0I
b0 H
bx G
1F
b0 E
1D
b0 C
bx B
0A
b0 @
0?
b0 >
bx =
0<
b0 ;
0:
b0 9
bx 8
07
b0 6
05
b0 4
bx 3
12
b0 1
10
b0 /
bx .
b0 -
b0 ,
bx +
bx *
b1011100010111101110110011000110110010000101111011100110111001001100001011011010101111101100101011110000111010001100101011011100111001101101001011011110110111000101110011101100110001101100100 )
b1001001011011100110100101110100 (
0'
0&
b0 %
0$
0#
b0 "
bx !
$end
#5000
bz 8
bz =
bz B
bz L
bz Q
bz V
1$
#10000
0$
#15000
1$
#20000
0$
#25000
1$
#30000
0$
#35000
1$
#40000
b10010010000101010011010100100100 1
b10010010000101010011010100100100 6
b10010010000101010011010100100100 ;
b10010010000101010011010100100100 @
b11111111111111111111111111111111 E
b11111111111111111111111111111111 J
b11111111111111111111111111111111 O
b11111111111111111111111111111111 T
1#
1'
b1111111111111111111111111111111110010010000101010011010100100100 %
b1111111111111111111111111111111110010010000101010011010100100100 -
b101011101010010 (
0$
b1000000100010010101111010000001 Y
b1 X
b1000000100010010101111010000001 +
b1 *
#45000
1$
#50000
b1000000100010010101111010000001 1
b1000000100010010101111010000001 6
b1000000100010010101111010000001 ;
b1000000100010010101111010000001 @
b0 E
b0 J
b0 O
b0 T
b1 /
b1 4
b1 9
b1 >
b1 C
b1 H
b1 M
b1 R
b100100001001101011000001001 Y
b10 X
b100100001001101011000001001 +
b10 *
b1000000100010010101111010000001 %
b1000000100010010101111010000001 -
b1 "
b1 ,
0$
#55000
1$
#60000
b100100001001101011000001001 1
b100100001001101011000001001 6
b100100001001101011000001001 ;
b100100001001101011000001001 @
b10 /
b10 4
b10 9
b10 >
b10 C
b10 H
b10 M
b10 R
b110001111100000101011001100011 Y
b11 X
b110001111100000101011001100011 +
b11 *
b100100001001101011000001001 %
b100100001001101011000001001 -
b10 "
b10 ,
0$
#65000
1$
#70000
b110001111100000101011001100011 1
b110001111100000101011001100011 6
b110001111100000101011001100011 ;
b110001111100000101011001100011 @
b11 /
b11 4
b11 9
b11 >
b11 C
b11 H
b11 M
b11 R
b1111111111111111111111111111111110000110101110010111101100001101 Y
b100 X
b10000110101110010111101100001101 +
b100 *
b110001111100000101011001100011 %
b110001111100000101011001100011 -
b11 "
b11 ,
0$
#75000
1$
#80000
b10000110101110010111101100001101 1
b10000110101110010111101100001101 6
b10000110101110010111101100001101 ;
b10000110101110010111101100001101 @
b11111111111111111111111111111111 E
b11111111111111111111111111111111 J
b11111111111111111111111111111111 O
b11111111111111111111111111111111 T
b100 /
b100 4
b100 9
b100 >
b100 C
b100 H
b100 M
b100 R
b1111111111111111111111111111111111000110110111111001100110001101 Y
b101 X
b11000110110111111001100110001101 +
b101 *
b1111111111111111111111111111111110000110101110010111101100001101 %
b1111111111111111111111111111111110000110101110010111101100001101 -
b100 "
b100 ,
0$
#85000
1$
#90000
b11000110110111111001100110001101 1
b11000110110111111001100110001101 6
b11000110110111111001100110001101 ;
b11000110110111111001100110001101 @
b101 /
b101 4
b101 9
b101 >
b101 C
b101 H
b101 M
b101 R
b110010110000101000010001100101 Y
b110 X
b110010110000101000010001100101 +
b110 *
b1111111111111111111111111111111111000110110111111001100110001101 %
b1111111111111111111111111111111111000110110111111001100110001101 -
b101 "
b101 ,
0$
#95000
1$
#100000
b110010110000101000010001100101 1
b110010110000101000010001100101 6
b110010110000101000010001100101 ;
b110010110000101000010001100101 @
b0 E
b0 J
b0 O
b0 T
b110 /
b110 4
b110 9
b110 >
b110 C
b110 H
b110 M
b110 R
b1001001101110101001000010010 Y
b111 X
b1001001101110101001000010010 +
b111 *
b110010110000101000010001100101 %
b110010110000101000010001100101 -
b110 "
b110 ,
0$
#105000
1$
#110000
b1001001101110101001000010010 1
b1001001101110101001000010010 6
b1001001101110101001000010010 ;
b1001001101110101001000010010 @
b111 /
b111 4
b111 9
b111 >
b111 C
b111 H
b111 M
b111 R
b1111111111111111111111111111111110000000111100111110001100000001 Y
b1000 X
b10000000111100111110001100000001 +
b1000 *
b1001001101110101001000010010 %
b1001001101110101001000010010 -
b111 "
b111 ,
0$
#115000
1$
#120000
b10000000111100111110001100000001 1
b10000000111100111110001100000001 6
b10000000111100111110001100000001 ;
b10000000111100111110001100000001 @
b11111111111111111111111111111111 E
b11111111111111111111111111111111 J
b11111111111111111111111111111111 O
b11111111111111111111111111111111 T
b1000 /
b1000 4
b1000 9
b1000 >
b1000 C
b1000 H
b1000 M
b1000 R
b1111111111111111111111111111111110000110110101111100110100001101 Y
b1001 X
b10000110110101111100110100001101 +
b1001 *
b1111111111111111111111111111111110000000111100111110001100000001 %
b1111111111111111111111111111111110000000111100111110001100000001 -
b1000 "
b1000 ,
0$
#125000
1$
#130000
b10000110110101111100110100001101 1
b10000110110101111100110100001101 6
b10000110110101111100110100001101 ;
b10000110110101111100110100001101 @
b1001 /
b1001 4
b1001 9
b1001 >
b1001 C
b1001 H
b1001 M
b1001 R
b1111111111111111111111111111111110111011001000111111000101110110 Y
b1010 X
b10111011001000111111000101110110 +
b1010 *
b1111111111111111111111111111111110000110110101111100110100001101 %
b1111111111111111111111111111111110000110110101111100110100001101 -
b1001 "
b1001 ,
0$
#135000
1$
#140000
b10111011001000111111000101110110 1
b10111011001000111111000101110110 6
b10111011001000111111000101110110 ;
b10111011001000111111000101110110 @
b1010 /
b1010 4
b1010 9
b1010 >
b1010 C
b1010 H
b1010 M
b1010 R
b1111111111111111111111111111111110011110100011011100110100111101 Y
b1011 X
b10011110100011011100110100111101 +
b1011 *
b1111111111111111111111111111111110111011001000111111000101110110 %
b1111111111111111111111111111111110111011001000111111000101110110 -
b1010 "
b1010 ,
0$
#145000
1$
#150000
b10011110100011011100110100111101 1
b10011110100011011100110100111101 6
b10011110100011011100110100111101 ;
b10011110100011011100110100111101 @
b1011 /
b1011 4
b1011 9
b1011 >
b1011 C
b1011 H
b1011 M
b1011 R
b1111111111111111111111111111111111110110110101000101011111101101 Y
b1100 X
b11110110110101000101011111101101 +
b1100 *
b1111111111111111111111111111111110011110100011011100110100111101 %
b1111111111111111111111111111111110011110100011011100110100111101 -
b1011 "
b1011 ,
0$
#155000
1$
#160000
b11110110110101000101011111101101 1
b11110110110101000101011111101101 6
b11110110110101000101011111101101 ;
b11110110110101000101011111101101 @
b1100 /
b1100 4
b1100 9
b1100 >
b1100 C
b1100 H
b1100 M
b1100 R
b1111111111111111111111111111111111000110001011011111011110001100 Y
b1101 X
b11000110001011011111011110001100 +
b1101 *
b1111111111111111111111111111111111110110110101000101011111101101 %
b1111111111111111111111111111111111110110110101000101011111101101 -
b1100 "
b1100 ,
0$
#165000
1$
#170000
b11000110001011011111011110001100 1
b11000110001011011111011110001100 6
b11000110001011011111011110001100 ;
b11000110001011011111011110001100 @
b1101 /
b1101 4
b1101 9
b1101 >
b1101 C
b1101 H
b1101 M
b1101 R
b1111111111111111111111111111111111111100111111011110100111111001 Y
b1110 X
b11111100111111011110100111111001 +
b1110 *
b1111111111111111111111111111111111000110001011011111011110001100 %
b1111111111111111111111111111111111000110001011011111011110001100 -
b1101 "
b1101 ,
0$
#175000
1$
#180000
b11111100111111011110100111111001 1
b11111100111111011110100111111001 6
b11111100111111011110100111111001 ;
b11111100111111011110100111111001 @
b1110 /
b1110 4
b1110 9
b1110 >
b1110 C
b1110 H
b1110 M
b1110 R
b1100011001101110010010011000110 Y
b1111 X
b1100011001101110010010011000110 +
b1111 *
b1111111111111111111111111111111111111100111111011110100111111001 %
b1111111111111111111111111111111111111100111111011110100111111001 -
b1110 "
b1110 ,
0$
#185000
1$
#190000
b1100011001101110010010011000110 1
b1100011001101110010010011000110 6
b1100011001101110010010011000110 ;
b1100011001101110010010011000110 @
b0 E
b0 J
b0 O
b0 T
b1111 /
b1111 4
b1111 9
b1111 >
b1111 C
b1111 H
b1111 M
b1111 R
b1100010111101111000010011000101 Y
b10000 X
b1100010111101111000010011000101 +
b10000 *
b1100011001101110010010011000110 %
b1100011001101110010010011000110 -
b1111 "
b1111 ,
0$
#195000
1$
#200000
00
02
0D
0F
15
17
1I
1K
b1100010111101111000010011000101 1
b1100010111101111000010011000101 6
b1100010111101111000010011000101 ;
b1100010111101111000010011000101 @
b0 /
b0 4
b0 9
b0 >
b0 C
b0 H
b0 M
b0 R
b1010101000100111101001010101010 Y
b10001 X
b1010101000100111101001010101010 +
b10001 *
b1100010111101111000010011000101 %
b1100010111101111000010011000101 -
b10000 "
b10000 ,
0$
#205000
bz 3
bx 8
bz G
bx L
1$
#210000
b1010101000100111101001010101010 1
b1010101000100111101001010101010 6
b1010101000100111101001010101010 ;
b1010101000100111101001010101010 @
b1 /
b1 4
b1 9
b1 >
b1 C
b1 H
b1 M
b1 R
b1111111111111111111111111111111111110010101011111111011111100101 Y
b10010 X
b11110010101011111111011111100101 +
b10010 *
b1010101000100111101001010101010 %
b1010101000100111101001010101010 -
b10001 "
b10001 ,
0$
#215000
1$
#220000
b11110010101011111111011111100101 1
b11110010101011111111011111100101 6
b11110010101011111111011111100101 ;
b11110010101011111111011111100101 @
b11111111111111111111111111111111 E
b11111111111111111111111111111111 J
b11111111111111111111111111111111 O
b11111111111111111111111111111111 T
b10 /
b10 4
b10 9
b10 >
b10 C
b10 H
b10 M
b10 R
b111011110100100111001001110111 Y
b10011 X
b111011110100100111001001110111 +
b10011 *
b1111111111111111111111111111111111110010101011111111011111100101 %
b1111111111111111111111111111111111110010101011111111011111100101 -
b10010 "
b10010 ,
0$
#225000
1$
#230000
b111011110100100111001001110111 1
b111011110100100111001001110111 6
b111011110100100111001001110111 ;
b111011110100100111001001110111 @
b0 E
b0 J
b0 O
b0 T
b11 /
b11 4
b11 9
b11 >
b11 C
b11 H
b11 M
b11 R
b1001001100101101011000010010 Y
b10100 X
b1001001100101101011000010010 +
b10100 *
b111011110100100111001001110111 %
b111011110100100111001001110111 -
b10011 "
b10011 ,
0$
#235000
1$
#240000
b1001001100101101011000010010 1
b1001001100101101011000010010 6
b1001001100101101011000010010 ;
b1001001100101101011000010010 @
b100 /
b100 4
b100 9
b100 >
b100 C
b100 H
b100 M
b100 R
b1111111111111111111111111111111111000111111011001101101110001111 Y
b10101 X
b11000111111011001101101110001111 +
b10101 *
b1001001100101101011000010010 %
b1001001100101101011000010010 -
b10100 "
b10100 ,
0$
#245000
1$
#250000
b11000111111011001101101110001111 1
b11000111111011001101101110001111 6
b11000111111011001101101110001111 ;
b11000111111011001101101110001111 @
b11111111111111111111111111111111 E
b11111111111111111111111111111111 J
b11111111111111111111111111111111 O
b11111111111111111111111111111111 T
b101 /
b101 4
b101 9
b101 >
b101 C
b101 H
b101 M
b101 R
b1111111111111111111111111111111111111001001100000110100111110010 Y
b10110 X
b11111001001100000110100111110010 +
b10110 *
b1111111111111111111111111111111111000111111011001101101110001111 %
b1111111111111111111111111111111111000111111011001101101110001111 -
b10101 "
b10101 ,
0$
#255000
1$
#260000
b11111001001100000110100111110010 1
b11111001001100000110100111110010 6
b11111001001100000110100111110010 ;
b11111001001100000110100111110010 @
b110 /
b110 4
b110 9
b110 >
b110 C
b110 H
b110 M
b110 R
b1100111011101101001011011001110 Y
b10111 X
b1100111011101101001011011001110 +
b10111 *
b1111111111111111111111111111111111111001001100000110100111110010 %
b1111111111111111111111111111111111111001001100000110100111110010 -
b10110 "
b10110 ,
0$
#265000
1$
#270000
b1100111011101101001011011001110 1
b1100111011101101001011011001110 6
b1100111011101101001011011001110 ;
b1100111011101101001011011001110 @
b0 E
b0 J
b0 O
b0 T
b111 /
b111 4
b111 9
b111 >
b111 C
b111 H
b111 M
b111 R
b1110100000000000111101011101000 Y
b11000 X
b1110100000000000111101011101000 +
b11000 *
b1100111011101101001011011001110 %
b1100111011101101001011011001110 -
b10111 "
b10111 ,
0$
#275000
1$
#280000
b1110100000000000111101011101000 1
b1110100000000000111101011101000 6
b1110100000000000111101011101000 ;
b1110100000000000111101011101000 @
b1000 /
b1000 4
b1000 9
b1000 >
b1000 C
b1000 H
b1000 M
b1000 R
b1100010110010100100111011000101 Y
b11001 X
b1100010110010100100111011000101 +
b11001 *
b1110100000000000111101011101000 %
b1110100000000000111101011101000 -
b11000 "
b11000 ,
0$
#285000
1$
#290000
b1100010110010100100111011000101 1
b1100010110010100100111011000101 6
b1100010110010100100111011000101 ;
b1100010110010100100111011000101 @
b1001 /
b1001 4
b1001 9
b1001 >
b1001 C
b1001 H
b1001 M
b1001 R
b1111111111111111111111111111111110101110010110000100100101011100 Y
b11010 X
b10101110010110000100100101011100 +
b11010 *
b1100010110010100100111011000101 %
b1100010110010100100111011000101 -
b11001 "
b11001 ,
0$
#295000
1$
#300000
b10101110010110000100100101011100 1
b10101110010110000100100101011100 6
b10101110010110000100100101011100 ;
b10101110010110000100100101011100 @
b11111111111111111111111111111111 E
b11111111111111111111111111111111 J
b11111111111111111111111111111111 O
b11111111111111111111111111111111 T
b1010 /
b1010 4
b1010 9
b1010 >
b1010 C
b1010 H
b1010 M
b1010 R
b1011110100011100010100010111101 Y
b11011 X
b1011110100011100010100010111101 +
b11011 *
b1111111111111111111111111111111110101110010110000100100101011100 %
b1111111111111111111111111111111110101110010110000100100101011100 -
b11010 "
b11010 ,
0$
#305000
1$
#310000
b1011110100011100010100010111101 1
b1011110100011100010100010111101 6
b1011110100011100010100010111101 ;
b1011110100011100010100010111101 @
b0 E
b0 J
b0 O
b0 T
b1011 /
b1011 4
b1011 9
b1011 >
b1011 C
b1011 H
b1011 M
b1011 R
b10110101010110101100000101101 Y
b11100 X
b10110101010110101100000101101 +
b11100 *
b1011110100011100010100010111101 %
b1011110100011100010100010111101 -
b11011 "
b11011 ,
0$
#315000
1$
#320000
b10110101010110101100000101101 1
b10110101010110101100000101101 6
b10110101010110101100000101101 ;
b10110101010110101100000101101 @
b1100 /
b1100 4
b1100 9
b1100 >
b1100 C
b1100 H
b1100 M
b1100 R
b110010101001110010011001100101 Y
b11101 X
b110010101001110010011001100101 +
b11101 *
b10110101010110101100000101101 %
b10110101010110101100000101101 -
b11100 "
b11100 ,
0$
#325000
1$
#330000
b110010101001110010011001100101 1
b110010101001110010011001100101 6
b110010101001110010011001100101 ;
b110010101001110010011001100101 @
b1101 /
b1101 4
b1101 9
b1101 >
b1101 C
b1101 H
b1101 M
b1101 R
b110001111011110110001001100011 Y
b11110 X
b110001111011110110001001100011 +
b11110 *
b110010101001110010011001100101 %
b110010101001110010011001100101 -
b11101 "
b11101 ,
0$
#335000
1$
#340000
b110001111011110110001001100011 1
b110001111011110110001001100011 6
b110001111011110110001001100011 ;
b110001111011110110001001100011 @
b1110 /
b1110 4
b1110 9
b1110 >
b1110 C
b1110 H
b1110 M
b1110 R
b1111111111111111111111111111111110000101011100111000011100001010 Y
b11111 X
b10000101011100111000011100001010 +
b11111 *
b110001111011110110001001100011 %
b110001111011110110001001100011 -
b11110 "
b11110 ,
0$
#345000
1$
#350000
b10000101011100111000011100001010 1
b10000101011100111000011100001010 6
b10000101011100111000011100001010 ;
b10000101011100111000011100001010 @
b11111111111111111111111111111111 E
b11111111111111111111111111111111 J
b11111111111111111111111111111111 O
b11111111111111111111111111111111 T
b1111 /
b1111 4
b1111 9
b1111 >
b1111 C
b1111 H
b1111 M
b1111 R
b1000000001110110010001010000000 Y
b100000 X
b1000000001110110010001010000000 +
b100000 *
b1111111111111111111111111111111110000101011100111000011100001010 %
b1111111111111111111111111111111110000101011100111000011100001010 -
b11111 "
b11111 ,
0$
#355000
1$
#360000
05
07
1:
1<
0I
0K
1N
1P
b1000000001110110010001010000000 1
b1000000001110110010001010000000 6
b1000000001110110010001010000000 ;
b1000000001110110010001010000000 @
b0 E
b0 J
b0 O
b0 T
b0 /
b0 4
b0 9
b0 >
b0 C
b0 H
b0 M
b0 R
b1111111111111111111111111111111110010000011001000010000100100000 Y
b100001 X
b10010000011001000010000100100000 +
b100001 *
b1000000001110110010001010000000 %
b1000000001110110010001010000000 -
b100000 "
b100000 ,
0$
#365000
bz 8
bx =
bz L
bx Q
1$
#370000
b10010000011001000010000100100000 1
b10010000011001000010000100100000 6
b10010000011001000010000100100000 ;
b10010000011001000010000100100000 @
b11111111111111111111111111111111 E
b11111111111111111111111111111111 J
b11111111111111111111111111111111 O
b11111111111111111111111111111111 T
b1 /
b1 4
b1 9
b1 >
b1 C
b1 H
b1 M
b1 R
b1111111111111111111111111111111111010101011110000100010110101010 Y
b100010 X
b11010101011110000100010110101010 +
b100010 *
b1111111111111111111111111111111110010000011001000010000100100000 %
b1111111111111111111111111111111110010000011001000010000100100000 -
b100001 "
b100001 ,
0$
#375000
1$
#380000
b11010101011110000100010110101010 1
b11010101011110000100010110101010 6
b11010101011110000100010110101010 ;
b11010101011110000100010110101010 @
b10 /
b10 4
b10 9
b10 >
b10 C
b10 H
b10 M
b10 R
b1001110110011001100110010011101 Y
b100011 X
b1001110110011001100110010011101 +
b100011 *
b1111111111111111111111111111111111010101011110000100010110101010 %
b1111111111111111111111111111111111010101011110000100010110101010 -
b100010 "
b100010 ,
0$
#385000
1$
#390000
b1001110110011001100110010011101 1
b1001110110011001100110010011101 6
b1001110110011001100110010011101 ;
b1001110110011001100110010011101 @
b0 E
b0 J
b0 O
b0 T
b11 /
b11 4
b11 9
b11 >
b11 C
b11 H
b11 M
b11 R
b1001011001000000011111010010110 Y
b100100 X
b1001011001000000011111010010110 +
b100100 *
b1001110110011001100110010011101 %
b1001110110011001100110010011101 -
b100011 "
b100011 ,
0$
#395000
1$
#400000
b1001011001000000011111010010110 1
b1001011001000000011111010010110 6
b1001011001000000011111010010110 ;
b1001011001000000011111010010110 @
b100 /
b100 4
b100 9
b100 >
b100 C
b100 H
b100 M
b100 R
b1001100000111011100000010011 Y
b100101 X
b1001100000111011100000010011 +
b100101 *
b1001011001000000011111010010110 %
b1001011001000000011111010010110 -
b100100 "
b100100 ,
0$
#405000
1$
#410000
b1001100000111011100000010011 1
b1001100000111011100000010011 6
b1001100000111011100000010011 ;
b1001100000111011100000010011 @
b101 /
b101 4
b101 9
b101 >
b101 C
b101 H
b101 M
b101 R
b110101111000011100000001101 Y
b100110 X
b110101111000011100000001101 +
b100110 *
b1001100000111011100000010011 %
b1001100000111011100000010011 -
b100101 "
b100101 ,
0$
#415000
1$
